README.txt
setup.py
collective/__init__.py
collective.contentrules.tagcondition.egg-info/PKG-INFO
collective.contentrules.tagcondition.egg-info/SOURCES.txt
collective.contentrules.tagcondition.egg-info/dependency_links.txt
collective.contentrules.tagcondition.egg-info/entry_points.txt
collective.contentrules.tagcondition.egg-info/namespace_packages.txt
collective.contentrules.tagcondition.egg-info/not-zip-safe
collective.contentrules.tagcondition.egg-info/paster_plugins.txt
collective.contentrules.tagcondition.egg-info/requires.txt
collective.contentrules.tagcondition.egg-info/top_level.txt
collective/contentrules/__init__.py
collective/contentrules/tagcondition/__init__.py
collective/contentrules/tagcondition/configure.zcml
collective/contentrules/tagcondition/tagcondition.py
collective/contentrules/tagcondition/tagparser.py
collective/contentrules/tagcondition/tests.py
docs/HISTORY.txt
docs/INSTALL.txt
docs/LICENSE.GPL
docs/LICENSE.txt