Metadata-Version: 1.0
Name: collective.contentrules.tagcondition
Version: 1.0
Summary: UNKNOWN
Home-page: http://svn.plone.org/svn/collective/collective.contentrules.tagcondition
Author: Michael Dunlap
Author-email: dunlapm@uw.edu
License: GPL
Platform: UNKNOWN
Classifier: Framework :: Plone
Classifier: Programming Language :: Python
